{"v":5,"entries":{"base-button--docs":{"id":"base-button--docs","title":"Base/Button","name":"Docs","importPath":"./src/stories/v1/base/button/button.stories.tsx","type":"docs","tags":["dev","test","autodocs"],"storiesImports":[]},"base-button--regular-button":{"type":"story","id":"base-button--regular-button","name":"Regular Button","title":"Base/Button","importPath":"./src/stories/v1/base/button/button.stories.tsx","componentPath":"./lib/v1/button","tags":["dev","test","autodocs"]},"base-button--loading-button":{"type":"story","id":"base-button--loading-button","name":"Loading Button","title":"Base/Button","importPath":"./src/stories/v1/base/button/button.stories.tsx","componentPath":"./lib/v1/button","tags":["dev","test","autodocs"]},"base-button--bordered-button":{"type":"story","id":"base-button--bordered-button","name":"Bordered Button","title":"Base/Button","importPath":"./src/stories/v1/base/button/button.stories.tsx","componentPath":"./lib/v1/button","tags":["dev","test","autodocs"]},"base-button--button-with-icon":{"type":"story","id":"base-button--button-with-icon","name":"Button With Icon","title":"Base/Button","importPath":"./src/stories/v1/base/button/button.stories.tsx","componentPath":"./lib/v1/button","tags":["dev","test","autodocs"]},"base-form-email-input--docs":{"id":"base-form-email-input--docs","title":"Base/Form/Email Input","name":"Docs","importPath":"./src/stories/v1/base/form/email-input.stories.tsx","type":"docs","tags":["dev","test","autodocs"],"storiesImports":[]},"base-form-email-input--default-email-input":{"type":"story","id":"base-form-email-input--default-email-input","name":"Default Email Input","title":"Base/Form/Email Input","importPath":"./src/stories/v1/base/form/email-input.stories.tsx","componentPath":"./lib/v1/form/email","tags":["dev","test","autodocs"]},"base-form-token-input--docs":{"id":"base-form-token-input--docs","title":"Base/Form/Token Input","name":"Docs","importPath":"./src/stories/v1/base/form/token-input.stories.tsx","type":"docs","tags":["dev","test","autodocs"],"storiesImports":[]},"base-form-token-input--default-token-input":{"type":"story","id":"base-form-token-input--default-token-input","name":"Default Token Input","title":"Base/Form/Token Input","importPath":"./src/stories/v1/base/form/token-input.stories.tsx","componentPath":"./lib/v1/form/token","tags":["dev","test","autodocs"]},"base-image--default":{"type":"story","id":"base-image--default","name":"Default","title":"Base/Image","importPath":"./src/stories/v1/base/image/image.stories.tsx","componentPath":"./lib/v1/image","tags":["dev","test"]},"base-image--rounded-image":{"type":"story","id":"base-image--rounded-image","name":"Rounded Image","title":"Base/Image","importPath":"./src/stories/v1/base/image/image.stories.tsx","componentPath":"./lib/v1/image","tags":["dev","test"]},"base-image--object-fit-cover":{"type":"story","id":"base-image--object-fit-cover","name":"Object Fit Cover","title":"Base/Image","importPath":"./src/stories/v1/base/image/image.stories.tsx","componentPath":"./lib/v1/image","tags":["dev","test"]},"base-image--with-hover-effect":{"type":"story","id":"base-image--with-hover-effect","name":"With Hover Effect","title":"Base/Image","importPath":"./src/stories/v1/base/image/image.stories.tsx","componentPath":"./lib/v1/image","tags":["dev","test"]},"base-image--placeholder-image":{"type":"story","id":"base-image--placeholder-image","name":"Placeholder Image","title":"Base/Image","importPath":"./src/stories/v1/base/image/image.stories.tsx","componentPath":"./lib/v1/image","tags":["dev","test"]},"base-image--custom-border-and-shadow":{"type":"story","id":"base-image--custom-border-and-shadow","name":"Custom Border And Shadow","title":"Base/Image","importPath":"./src/stories/v1/base/image/image.stories.tsx","componentPath":"./lib/v1/image","tags":["dev","test"]},"base-link--default":{"type":"story","id":"base-link--default","name":"Default","title":"Base/Link","importPath":"./src/stories/v1/base/link/link.stories.tsx","componentPath":"./lib/v1/link","tags":["dev","test"]},"base-link--custom-link":{"type":"story","id":"base-link--custom-link","name":"Custom Link","title":"Base/Link","importPath":"./src/stories/v1/base/link/link.stories.tsx","componentPath":"./lib/v1/link","tags":["dev","test"]},"base-logo--docs":{"id":"base-logo--docs","title":"Base/Logo","name":"Docs","importPath":"./src/stories/v1/base/logo/logo.stories.tsx","type":"docs","tags":["dev","test","autodocs"],"storiesImports":[]},"base-logo--default-logo":{"type":"story","id":"base-logo--default-logo","name":"Default Logo","title":"Base/Logo","importPath":"./src/stories/v1/base/logo/logo.stories.tsx","componentPath":"./lib/v1/logo","tags":["dev","test","autodocs"]},"base-typography--docs":{"id":"base-typography--docs","title":"Base/Typography","name":"Docs","importPath":"./src/stories/v1/base/typography/typography.stories.tsx","type":"docs","tags":["dev","test","autodocs"],"storiesImports":[]},"base-typography--default":{"type":"story","id":"base-typography--default","name":"Default","title":"Base/Typography","importPath":"./src/stories/v1/base/typography/typography.stories.tsx","componentPath":"./lib/v1/typography","tags":["dev","test","autodocs"]},"base-typography--heading-1":{"type":"story","id":"base-typography--heading-1","name":"Heading 1","title":"Base/Typography","importPath":"./src/stories/v1/base/typography/typography.stories.tsx","componentPath":"./lib/v1/typography","tags":["dev","test","autodocs"]},"composites-avatar--docs":{"id":"composites-avatar--docs","title":"Composites/Avatar","name":"Docs","importPath":"./src/stories/v1/composites/avatar/avatar.stories.tsx","type":"docs","tags":["dev","test","autodocs"],"storiesImports":[]},"composites-avatar--default":{"type":"story","id":"composites-avatar--default","name":"Default","title":"Composites/Avatar","importPath":"./src/stories/v1/composites/avatar/avatar.stories.tsx","componentPath":"./lib/v1/avatar","tags":["dev","test","autodocs"]},"composites-banner--docs":{"id":"composites-banner--docs","title":"Composites/Banner","name":"Docs","importPath":"./src/stories/v1/composites/banner/banner.stories.tsx","type":"docs","tags":["dev","test","autodocs"],"storiesImports":[]},"composites-banner--basic-banner":{"type":"story","id":"composites-banner--basic-banner","name":"Basic Banner","title":"Composites/Banner","importPath":"./src/stories/v1/composites/banner/banner.stories.tsx","componentPath":"./lib/v1/banner","tags":["dev","test","autodocs"]},"composites-divider--docs":{"type":"story","id":"composites-divider--docs","name":"Docs","title":"Composites/Divider","importPath":"./src/stories/v1/composites/divider/divider.stories.tsx","componentPath":"./lib/v1/divider","tags":["dev","test"]},"composites-icon--docs":{"id":"composites-icon--docs","title":"Composites/Icon","name":"Docs","importPath":"./src/stories/v1/composites/icon/icon.stories.tsx","type":"docs","tags":["dev","test","autodocs"],"storiesImports":[]},"composites-icon--heyo":{"type":"story","id":"composites-icon--heyo","name":"Heyo","title":"Composites/Icon","importPath":"./src/stories/v1/composites/icon/icon.stories.tsx","componentPath":"./lib/v1/icon","tags":["dev","test","autodocs"]},"composites-notifications--docs":{"id":"composites-notifications--docs","title":"Composites/Notifications","name":"Docs","importPath":"./src/stories/v1/composites/notification/notification.stories.tsx","type":"docs","tags":["dev","test","autodocs"],"storiesImports":[]},"composites-notifications--default":{"type":"story","id":"composites-notifications--default","name":"Default","title":"Composites/Notifications","importPath":"./src/stories/v1/composites/notification/notification.stories.tsx","componentPath":"./lib/v1/notification","tags":["dev","test","autodocs"]},"composites-sidebar--default":{"type":"story","id":"composites-sidebar--default","name":"Default","title":"Composites/Sidebar","importPath":"./src/stories/v1/composites/sidebar/sidebar-wrapper.stories.tsx","componentPath":"./lib/v1/sidebar","tags":["dev","test"]},"composites-task--docs":{"id":"composites-task--docs","title":"Composites/Task","name":"Docs","importPath":"./src/stories/v1/composites/task/task.stories.tsx","type":"docs","tags":["dev","test","autodocs"],"storiesImports":[]},"composites-task--default":{"type":"story","id":"composites-task--default","name":"Default","title":"Composites/Task","importPath":"./src/stories/v1/composites/task/task.stories.tsx","componentPath":"./lib/v1/task","tags":["dev","test","autodocs"]},"composites-task--archived":{"type":"story","id":"composites-task--archived","name":"Archived","title":"Composites/Task","importPath":"./src/stories/v1/composites/task/task.stories.tsx","componentPath":"./lib/v1/task","tags":["dev","test","autodocs"]},"screens-dashboard-user-dashboard--user-dashboard-story":{"type":"story","id":"screens-dashboard-user-dashboard--user-dashboard-story","name":"User Dashboard Story","title":"Screens/Dashboard/User Dashboard","importPath":"./src/stories/v1/screens/dashboard/user-dashboard.stories.tsx","componentPath":"./src/stories/v1/screens/dashboard/user-dashboard.tsx","tags":["dev","test"]}}}